<StructureDefinition xmlns="http://hl7.org/fhir">
  <id value="be-model-immunization" />
  <url value="https://www.hl7belgium.org/fhir/StructureDefinition/be-model-immunization" />
  <name value="BEImmunization" />
  <status value="draft" />
  <description value="This is the logical model of the patient's immunization entries in an immunization or vaccination record. The patient immunization record of several entries as modeled here." />
  <fhirVersion value="4.0.1" />
  <kind value="logical" />
  <abstract value="false" />
  <type value="BEImmunization" />
  <baseDefinition value="http://hl7.org/fhir/StructureDefinition/Resource" />
  <derivation value="specialization" />
  <differential>
    <element id="BEImmunization">
      <path value="BEImmunization" />
      <short value="A record of an immunization or vaccination" />
      <min value="0" />
      <max value="*" />
    </element>
    <element id="BEImmunization.identifier">
      <path value="BEImmunization.identifier" />
      <short value="The business identifier(s) for the immunization entry" />
      <definition value="The business identifier(s) for the immunization entry - This is an optional attribute, used for example to track an entry throughout its lifecycle, or across vaults." />
      <min value="0" />
      <max value="1" />
      <type>
        <code value="Identifier" />
      </type>
    </element>
    <element id="BEImmunization.status">
      <path value="BEImmunization.status" />
      <short value="The status of this immunization record entry" />
      <definition value="The status of the immunization record entry - whether it is active, entered in error, etc." />
      <min value="1" />
      <max value="1" />
      <type>
        <code value="code" />
        <profile value="http://hl7.org/fhir/StructureDefinition/code" />
      </type>
    </element>
    <element id="BEImmunization.statusReason">
      <path value="BEImmunization.statusReason" />
      <short value="The reason for the status e.g. entered in error because ..." />
      <definition value="Supporting reason for status information....." />
      <min value="0" />
      <max value="1" />
      <type>
        <code value="CodeableConcept" />
        <profile value="http://hl7.org/fhir/StructureDefinition/CodeableConcept" />
      </type>
    </element>


	
    <element id="BEImmunization.patient">
      <path value="BEImmunization.patient" />
      <short value="The patient that received immunization." />
      <definition value="The patient that has received the immunization." />
      <min value="1" />
      <max value="1" />
      <type>
        <code value="Reference" />
        <targetProfile value="https://www.ehealth.fgov.be/standards/fhir/StructureDefinition/be-patient" />
      </type>
    </element>



    <element id="BEImmunization.vaccineCode">
      <path value="BEImmunization.vaccineCode" />
      <short value="The target of the immunization - the disease that the immunization action is protecting against - e.g. Polio, Tetanus, HPV" />
      <definition value="The target of the immunization - the disease that the immunization action is protecting against. This should be a coded value." />
      <min value="0" />
      <max value="1" />
      <type>
        <code value="CodeableConcept" />
      </type>
    </element>


	
	
    <element id="BEImmunization.dateTime">
      <path value="BEImmunization.dateTime" />
      <short value="The dateTime when the immunization has been recorded" />
      <definition value="The date and/or time when the immunization administration has been recorded" />
      <min value="0" />
      <max value="1" />
      <type>
        <code value="dateTime" />
        <profile value="http://hl7.org/fhir/StructureDefinition/dateTime" />
      </type>
    </element>
	
    <element id="BEImmunization.immunizationPlan">
      <path value="BEImmunization.immunizationPlan" />
      <short value="The patient-specific order or recommendation for the immunization" />
      <definition value="The patient-specific order or recommendation for the immunization, for example a prescription or a request for immunization for a patient by a physician, for example for optional vaccines." />
      <min value="0" />
      <max value="1" />
      <type>
        <code value="Reference" />
      </type>
    </element>

    <element id="BEImmunization.protocol">
      <path value="BEImmunization.protocol" />
      <short value="The vaccination plan or protocol (not patient-specific) that this immunization is fulfilling" />
      <definition value="The vaccination plan or protocol (not patient-specific) that this immunization is fulfilling. For example 'Basisvaccinatieschema'" />
      <min value="0" />
      <max value="1" />
      <type>
        <code value="Reference" />
      </type>
    </element>

    <element id="BEImmunization.type">
      <path value="BEImmunization.type" />
      <short value="The type of immunization action - for example first dose or reinforcement." />
      <definition value="The type of immunization action - for example first dose or reinforcement." />
      <min value="0" />
      <max value="1" />
      <type>
        <code value="code" />
      </type>
    </element>
	
	
    <element id="BEImmunization.reporter">
      <path value="BEImmunization.reporter" />
      <short value="The professional that recorded the administration of the vaccine" />
      <definition value="The professional that recorded the administration of the vaccine." />
      <min value="0" />
      <max value="1" />
      <type>
        <code value="Reference" />
        <targetProfile value="https://www.ehealth.fgov.be/standards/fhir/StructureDefinition/be-practitioner"/>
      </type>
    </element>

    <element id="BEImmunization.recorded">
      <path value="BEImmunization.recorded" />
      <short value="The date and time when the administration of the vaccine was recorded" />
      <definition value="The date and time when the administration of the vaccine was recorded - typically used when the vaccine event is recorded a posteriori." />
      <min value="0" />
      <max value="1" />
      <type>
        <code value="dateTime" />
      </type>
    </element>
	
    <element id="BEImmunization.performer">
      <path value="BEImmunization.performer" />
      <short value="The professional that administered the medication" />
      <definition value="The professional that administered the medication." />
      <min value="0" />
      <max value="1" />
      <type>
        <code value="Reference" />
        <targetProfile value="https://www.ehealth.fgov.be/standards/fhir/StructureDefinition/be-practitioner"/>
      </type>
    </element>
	


    <element id="BEImmunization.route">
      <path value="BEImmunization.route" />
      <short value="The route of administration." />
      <definition value="The route of administration for the vaccine. This can be free text (not desired) or a code" />
      <min value="0" />
      <max value="1" />
      <type>
        <code value="CodeableConcept" />
      </type>
    </element>



    <element id="BEImmunization.administeredProduct">
      <path value="BEImmunization.administeredProduct" />
      <short value="The details of the product that was administered." />
      <definition value="" />
      <min value="0" />
      <max value="1" />
      <type>
        <code value="BackboneElement" />
      </type>
    </element>


    <element id="BEImmunization.administeredProduct.product">
      <path value="BEImmunization.administeredProduct.product" />
      <short value="The actual product that was administered. This can be just text (not desired), or a code (e.g. 1696392 = Neisvac C Dos 0,5ml) or a reference to an actual Medication product (e.g. http://server/Medication/1696392)" />
      <definition value="" />
      <min value="0" />
      <max value="1" />
      <type>
        <code value="CodeableReference" />
      </type>
    </element>


    <element id="BEImmunization.administeredProduct.lotNumber">
      <path value="BEImmunization.administeredProduct.lotNumber" />
      <short value="The lot number" />
      <definition value="The lot number" />
      <min value="0" />
      <max value="1" />
      <type>
        <code value="string" />
      </type>
    </element>

    <element id="BEImmunization.administeredProduct.expirationDate">
      <path value="BEImmunization.administeredProduct.expirationDate" />
      <short value="The expiration date of the product." />
      <definition value="The expiration date of the product." />
      <min value="0" />
      <max value="1" />
      <type>
        <code value="Date" />
      </type>
    </element>



    <element id="BEImmunization.location">
      <path value="BEImmunization.location" />
      <short value="The location of the immunization." />
      <definition value="The location where the immunization administration was performed. This can be a text (e.g. 'at the physician's office' or a code e.g. '00078' meaning 'patient's home' or a resource (Location) if one exists e.g. 'Location/kind-en-gezin-092375' which could be defining 'Kind en Gezin Gent Koepoortkaai' " />
      <min value="0" />
      <max value="1" />
      <type>
        <code value="CodeableReference" />
      </type>
    </element>




    <element id="BEImmunization.note">
      <path value="BEImmunization.note" />
      <short value="Additional notes for the immunization." />
      <definition value="Additional notes for the immunization" />
      <min value="0" />
      <max value="1" />
      <type>
        <code value="Attachment" />
        <profile value="http://hl7.org/fhir/StructureDefinition/Attachment" />
      </type>
    </element>






  </differential>
</StructureDefinition>